<?xml version="1.0" encoding="UTF-8" standalone="yes"?>
<dgm:dataModel xmlns:dgm="http://schemas.openxmlformats.org/drawingml/2006/diagram" xmlns:a="http://schemas.openxmlformats.org/drawingml/2006/main"><dgm:ptLst><dgm:pt modelId="{85EE8DA9-04DC-455E-BEBE-E95B1B8E8B02}" type="doc"><dgm:prSet loTypeId="urn:microsoft.com/office/officeart/2005/8/layout/process2" loCatId="process" qsTypeId="urn:microsoft.com/office/officeart/2005/8/quickstyle/simple1" qsCatId="simple" csTypeId="urn:microsoft.com/office/officeart/2005/8/colors/accent0_1" csCatId="mainScheme" phldr="1"/><dgm:spPr/></dgm:pt><dgm:pt modelId="{FAC1D642-4131-4165-956D-4755DF760E9B}"><dgm:prSet phldrT="[Text]" custT="1"/><dgm:spPr/><dgm:t><a:bodyPr/><a:lstStyle/><a:p><a:r><a:rPr lang="en-US" sz="1300" b="0"><a:latin typeface="Times New Roman" panose="02020603050405020304" pitchFamily="18" charset="0"/><a:cs typeface="Times New Roman" panose="02020603050405020304" pitchFamily="18" charset="0"/></a:rPr><a:t>Phân tích thị trường và đánh giá tiềm năng</a:t></a:r></a:p></dgm:t></dgm:pt><dgm:pt modelId="{3B866494-B66B-47F7-8E61-065A264561F8}" type="parTrans" cxnId="{B9EA87D1-4218-46BE-A635-A8D943634C3D}"><dgm:prSet/><dgm:spPr/><dgm:t><a:bodyPr/><a:lstStyle/><a:p><a:endParaRPr lang="en-US"/></a:p></dgm:t></dgm:pt><dgm:pt modelId="{1BF5E5EF-C969-48A4-98E6-E2BF08C5EE4D}" type="sibTrans" cxnId="{B9EA87D1-4218-46BE-A635-A8D943634C3D}"><dgm:prSet/><dgm:spPr/><dgm:t><a:bodyPr/><a:lstStyle/><a:p><a:endParaRPr lang="en-US"/></a:p></dgm:t></dgm:pt><dgm:pt modelId="{979D5E46-5707-4FE3-83C6-FCCD3131F1DD}"><dgm:prSet phldrT="[Text]" custT="1"/><dgm:spPr/><dgm:t><a:bodyPr/><a:lstStyle/><a:p><a:r><a:rPr lang="en-US" sz="1300" b="0"><a:latin typeface="Times New Roman" panose="02020603050405020304" pitchFamily="18" charset="0"/><a:cs typeface="Times New Roman" panose="02020603050405020304" pitchFamily="18" charset="0"/></a:rPr><a:t>Xác định khách hàng mục tiêu và phân khúc thị trường</a:t></a:r></a:p></dgm:t></dgm:pt><dgm:pt modelId="{A5BA856F-CDD5-467F-AED9-A6F53B78CA73}" type="parTrans" cxnId="{A91BF3C8-B4C2-4E5A-9B45-053C94FABE21}"><dgm:prSet/><dgm:spPr/><dgm:t><a:bodyPr/><a:lstStyle/><a:p><a:endParaRPr lang="en-US"/></a:p></dgm:t></dgm:pt><dgm:pt modelId="{3E3C9E13-D532-4240-861B-61465A101B7E}" type="sibTrans" cxnId="{A91BF3C8-B4C2-4E5A-9B45-053C94FABE21}"><dgm:prSet/><dgm:spPr/><dgm:t><a:bodyPr/><a:lstStyle/><a:p><a:endParaRPr lang="en-US"/></a:p></dgm:t></dgm:pt><dgm:pt modelId="{CE9C2ADF-3546-4D19-879D-AA1F0A6B6A00}"><dgm:prSet phldrT="[Text]" custT="1"/><dgm:spPr/><dgm:t><a:bodyPr/><a:lstStyle/><a:p><a:r><a:rPr lang="en-US" sz="1300" b="0"><a:latin typeface="Times New Roman" panose="02020603050405020304" pitchFamily="18" charset="0"/><a:cs typeface="Times New Roman" panose="02020603050405020304" pitchFamily="18" charset="0"/></a:rPr><a:t>Thiết kế chiến lược tiếp cận khách hàng mục tiêu</a:t></a:r></a:p></dgm:t></dgm:pt><dgm:pt modelId="{C0781A16-16F4-43F6-9BA9-60FFBFC26D01}" type="parTrans" cxnId="{65E78142-9099-49A5-8BD1-2C4E637E4DB8}"><dgm:prSet/><dgm:spPr/><dgm:t><a:bodyPr/><a:lstStyle/><a:p><a:endParaRPr lang="en-US"/></a:p></dgm:t></dgm:pt><dgm:pt modelId="{58614A8E-89EF-4F11-B611-F2050B197452}" type="sibTrans" cxnId="{65E78142-9099-49A5-8BD1-2C4E637E4DB8}"><dgm:prSet/><dgm:spPr/><dgm:t><a:bodyPr/><a:lstStyle/><a:p><a:endParaRPr lang="en-US"/></a:p></dgm:t></dgm:pt><dgm:pt modelId="{028CE4FE-C1CA-4243-AC43-8A3B69987633}"><dgm:prSet phldrT="[Text]" custT="1"/><dgm:spPr/><dgm:t><a:bodyPr/><a:lstStyle/><a:p><a:r><a:rPr lang="en-US" sz="1300" b="0"><a:latin typeface="Times New Roman" panose="02020603050405020304" pitchFamily="18" charset="0"/><a:cs typeface="Times New Roman" panose="02020603050405020304" pitchFamily="18" charset="0"/></a:rPr><a:t>Triển khai chiến dịch marketing và bán hàng</a:t></a:r></a:p></dgm:t></dgm:pt><dgm:pt modelId="{F361823E-B6D5-4600-B509-D28A919D22BA}" type="parTrans" cxnId="{6BDE2AED-AFA3-4FB2-A416-3B2150C32B92}"><dgm:prSet/><dgm:spPr/><dgm:t><a:bodyPr/><a:lstStyle/><a:p><a:endParaRPr lang="en-US"/></a:p></dgm:t></dgm:pt><dgm:pt modelId="{7DE6B735-D8BA-4383-8518-E7F188E33349}" type="sibTrans" cxnId="{6BDE2AED-AFA3-4FB2-A416-3B2150C32B92}"><dgm:prSet/><dgm:spPr/><dgm:t><a:bodyPr/><a:lstStyle/><a:p><a:endParaRPr lang="en-US"/></a:p></dgm:t></dgm:pt><dgm:pt modelId="{D8DDE4C9-5B1D-445A-8F8C-F0A953B28386}"><dgm:prSet phldrT="[Text]" custT="1"/><dgm:spPr/><dgm:t><a:bodyPr/><a:lstStyle/><a:p><a:r><a:rPr lang="en-US" sz="1300" b="0"><a:latin typeface="Times New Roman" panose="02020603050405020304" pitchFamily="18" charset="0"/><a:cs typeface="Times New Roman" panose="02020603050405020304" pitchFamily="18" charset="0"/></a:rPr><a:t>Theo dõi kết quả và tối ưu hóa</a:t></a:r></a:p></dgm:t></dgm:pt><dgm:pt modelId="{E3311A88-C6B4-4B9D-AE6D-B76F72D7BAE6}" type="parTrans" cxnId="{15AFAA56-A35E-4946-ADBF-BB199A1A0CD4}"><dgm:prSet/><dgm:spPr/><dgm:t><a:bodyPr/><a:lstStyle/><a:p><a:endParaRPr lang="en-US"/></a:p></dgm:t></dgm:pt><dgm:pt modelId="{9FC82D2B-1FA6-4845-82DA-15F7AAB3191F}" type="sibTrans" cxnId="{15AFAA56-A35E-4946-ADBF-BB199A1A0CD4}"><dgm:prSet/><dgm:spPr/><dgm:t><a:bodyPr/><a:lstStyle/><a:p><a:endParaRPr lang="en-US"/></a:p></dgm:t></dgm:pt><dgm:pt modelId="{FBBDC216-FD4E-4F75-9122-C693ECF22FAA}" type="pres"><dgm:prSet presAssocID="{85EE8DA9-04DC-455E-BEBE-E95B1B8E8B02}" presName="linearFlow" presStyleCnt="0"><dgm:presLayoutVars><dgm:resizeHandles val="exact"/></dgm:presLayoutVars></dgm:prSet><dgm:spPr/></dgm:pt><dgm:pt modelId="{CF8D8D67-02F6-4BC6-AC36-E7F553406E0E}" type="pres"><dgm:prSet presAssocID="{FAC1D642-4131-4165-956D-4755DF760E9B}" presName="node" presStyleLbl="node1" presStyleIdx="0" presStyleCnt="5" custScaleX="211248"><dgm:presLayoutVars><dgm:bulletEnabled val="1"/></dgm:presLayoutVars></dgm:prSet><dgm:spPr/></dgm:pt><dgm:pt modelId="{3BD5F3ED-C9DA-45B5-B47E-7C8B2178E406}" type="pres"><dgm:prSet presAssocID="{1BF5E5EF-C969-48A4-98E6-E2BF08C5EE4D}" presName="sibTrans" presStyleLbl="sibTrans2D1" presStyleIdx="0" presStyleCnt="4"/><dgm:spPr/></dgm:pt><dgm:pt modelId="{5AEB064E-6249-4BCE-9AB5-DCDD47D35370}" type="pres"><dgm:prSet presAssocID="{1BF5E5EF-C969-48A4-98E6-E2BF08C5EE4D}" presName="connectorText" presStyleLbl="sibTrans2D1" presStyleIdx="0" presStyleCnt="4"/><dgm:spPr/></dgm:pt><dgm:pt modelId="{2CE34339-7BFE-4237-A512-63B0485362FF}" type="pres"><dgm:prSet presAssocID="{979D5E46-5707-4FE3-83C6-FCCD3131F1DD}" presName="node" presStyleLbl="node1" presStyleIdx="1" presStyleCnt="5" custScaleX="211205"><dgm:presLayoutVars><dgm:bulletEnabled val="1"/></dgm:presLayoutVars></dgm:prSet><dgm:spPr/></dgm:pt><dgm:pt modelId="{2E5D365C-8143-45DB-BC59-E2246545D519}" type="pres"><dgm:prSet presAssocID="{3E3C9E13-D532-4240-861B-61465A101B7E}" presName="sibTrans" presStyleLbl="sibTrans2D1" presStyleIdx="1" presStyleCnt="4"/><dgm:spPr/></dgm:pt><dgm:pt modelId="{CE053936-2CDC-4F1A-AFC0-510D7BE55341}" type="pres"><dgm:prSet presAssocID="{3E3C9E13-D532-4240-861B-61465A101B7E}" presName="connectorText" presStyleLbl="sibTrans2D1" presStyleIdx="1" presStyleCnt="4"/><dgm:spPr/></dgm:pt><dgm:pt modelId="{06FF23AE-5139-4417-AC57-FE8A80B517B9}" type="pres"><dgm:prSet presAssocID="{CE9C2ADF-3546-4D19-879D-AA1F0A6B6A00}" presName="node" presStyleLbl="node1" presStyleIdx="2" presStyleCnt="5" custScaleX="211205"><dgm:presLayoutVars><dgm:bulletEnabled val="1"/></dgm:presLayoutVars></dgm:prSet><dgm:spPr/></dgm:pt><dgm:pt modelId="{F57D250A-67D8-41EF-AFCF-2442BA3F2D23}" type="pres"><dgm:prSet presAssocID="{58614A8E-89EF-4F11-B611-F2050B197452}" presName="sibTrans" presStyleLbl="sibTrans2D1" presStyleIdx="2" presStyleCnt="4"/><dgm:spPr/></dgm:pt><dgm:pt modelId="{55BA79EA-8102-44BD-82F2-C7799D9B298B}" type="pres"><dgm:prSet presAssocID="{58614A8E-89EF-4F11-B611-F2050B197452}" presName="connectorText" presStyleLbl="sibTrans2D1" presStyleIdx="2" presStyleCnt="4"/><dgm:spPr/></dgm:pt><dgm:pt modelId="{0F81E002-8D1F-4D4C-BDDC-BFC08B7ECC2E}" type="pres"><dgm:prSet presAssocID="{028CE4FE-C1CA-4243-AC43-8A3B69987633}" presName="node" presStyleLbl="node1" presStyleIdx="3" presStyleCnt="5" custScaleX="211205"><dgm:presLayoutVars><dgm:bulletEnabled val="1"/></dgm:presLayoutVars></dgm:prSet><dgm:spPr/></dgm:pt><dgm:pt modelId="{85F6C259-8509-4F54-8CC0-BBC15F1C043B}" type="pres"><dgm:prSet presAssocID="{7DE6B735-D8BA-4383-8518-E7F188E33349}" presName="sibTrans" presStyleLbl="sibTrans2D1" presStyleIdx="3" presStyleCnt="4"/><dgm:spPr/></dgm:pt><dgm:pt modelId="{3B8DD56D-B690-4851-91A9-E833B81AE722}" type="pres"><dgm:prSet presAssocID="{7DE6B735-D8BA-4383-8518-E7F188E33349}" presName="connectorText" presStyleLbl="sibTrans2D1" presStyleIdx="3" presStyleCnt="4"/><dgm:spPr/></dgm:pt><dgm:pt modelId="{1CDBEB51-C06C-4495-9F1F-B3A13501E2CD}" type="pres"><dgm:prSet presAssocID="{D8DDE4C9-5B1D-445A-8F8C-F0A953B28386}" presName="node" presStyleLbl="node1" presStyleIdx="4" presStyleCnt="5" custScaleX="211205"><dgm:presLayoutVars><dgm:bulletEnabled val="1"/></dgm:presLayoutVars></dgm:prSet><dgm:spPr/></dgm:pt></dgm:ptLst><dgm:cxnLst><dgm:cxn modelId="{6DE7A339-4EBB-4840-B2FE-5DC49C4872C2}" type="presOf" srcId="{58614A8E-89EF-4F11-B611-F2050B197452}" destId="{55BA79EA-8102-44BD-82F2-C7799D9B298B}" srcOrd="1" destOrd="0" presId="urn:microsoft.com/office/officeart/2005/8/layout/process2"/><dgm:cxn modelId="{65E78142-9099-49A5-8BD1-2C4E637E4DB8}" srcId="{85EE8DA9-04DC-455E-BEBE-E95B1B8E8B02}" destId="{CE9C2ADF-3546-4D19-879D-AA1F0A6B6A00}" srcOrd="2" destOrd="0" parTransId="{C0781A16-16F4-43F6-9BA9-60FFBFC26D01}" sibTransId="{58614A8E-89EF-4F11-B611-F2050B197452}"/><dgm:cxn modelId="{9CA49B62-A7DD-4842-8D96-C4C770B1A388}" type="presOf" srcId="{85EE8DA9-04DC-455E-BEBE-E95B1B8E8B02}" destId="{FBBDC216-FD4E-4F75-9122-C693ECF22FAA}" srcOrd="0" destOrd="0" presId="urn:microsoft.com/office/officeart/2005/8/layout/process2"/><dgm:cxn modelId="{659C7746-7C3C-4509-8343-88E560C200D2}" type="presOf" srcId="{58614A8E-89EF-4F11-B611-F2050B197452}" destId="{F57D250A-67D8-41EF-AFCF-2442BA3F2D23}" srcOrd="0" destOrd="0" presId="urn:microsoft.com/office/officeart/2005/8/layout/process2"/><dgm:cxn modelId="{1514544F-C047-4023-8FB3-58E5A3C816ED}" type="presOf" srcId="{7DE6B735-D8BA-4383-8518-E7F188E33349}" destId="{3B8DD56D-B690-4851-91A9-E833B81AE722}" srcOrd="1" destOrd="0" presId="urn:microsoft.com/office/officeart/2005/8/layout/process2"/><dgm:cxn modelId="{B4BD3471-5455-4808-9A2C-2466C3CC607E}" type="presOf" srcId="{3E3C9E13-D532-4240-861B-61465A101B7E}" destId="{2E5D365C-8143-45DB-BC59-E2246545D519}" srcOrd="0" destOrd="0" presId="urn:microsoft.com/office/officeart/2005/8/layout/process2"/><dgm:cxn modelId="{15AFAA56-A35E-4946-ADBF-BB199A1A0CD4}" srcId="{85EE8DA9-04DC-455E-BEBE-E95B1B8E8B02}" destId="{D8DDE4C9-5B1D-445A-8F8C-F0A953B28386}" srcOrd="4" destOrd="0" parTransId="{E3311A88-C6B4-4B9D-AE6D-B76F72D7BAE6}" sibTransId="{9FC82D2B-1FA6-4845-82DA-15F7AAB3191F}"/><dgm:cxn modelId="{F3DEFA56-BBD7-4BF0-90A9-0EBD28F2D4AE}" type="presOf" srcId="{7DE6B735-D8BA-4383-8518-E7F188E33349}" destId="{85F6C259-8509-4F54-8CC0-BBC15F1C043B}" srcOrd="0" destOrd="0" presId="urn:microsoft.com/office/officeart/2005/8/layout/process2"/><dgm:cxn modelId="{8D40457B-C1EE-464D-B5B3-03D8A7B46051}" type="presOf" srcId="{979D5E46-5707-4FE3-83C6-FCCD3131F1DD}" destId="{2CE34339-7BFE-4237-A512-63B0485362FF}" srcOrd="0" destOrd="0" presId="urn:microsoft.com/office/officeart/2005/8/layout/process2"/><dgm:cxn modelId="{8E3E32A3-8A35-4815-BB06-B78B4BADCBFD}" type="presOf" srcId="{028CE4FE-C1CA-4243-AC43-8A3B69987633}" destId="{0F81E002-8D1F-4D4C-BDDC-BFC08B7ECC2E}" srcOrd="0" destOrd="0" presId="urn:microsoft.com/office/officeart/2005/8/layout/process2"/><dgm:cxn modelId="{B275A0AF-30C9-414D-ABF8-C1A7C8E43425}" type="presOf" srcId="{D8DDE4C9-5B1D-445A-8F8C-F0A953B28386}" destId="{1CDBEB51-C06C-4495-9F1F-B3A13501E2CD}" srcOrd="0" destOrd="0" presId="urn:microsoft.com/office/officeart/2005/8/layout/process2"/><dgm:cxn modelId="{D52140B5-5B49-44B9-A670-D940098BF72E}" type="presOf" srcId="{3E3C9E13-D532-4240-861B-61465A101B7E}" destId="{CE053936-2CDC-4F1A-AFC0-510D7BE55341}" srcOrd="1" destOrd="0" presId="urn:microsoft.com/office/officeart/2005/8/layout/process2"/><dgm:cxn modelId="{A91BF3C8-B4C2-4E5A-9B45-053C94FABE21}" srcId="{85EE8DA9-04DC-455E-BEBE-E95B1B8E8B02}" destId="{979D5E46-5707-4FE3-83C6-FCCD3131F1DD}" srcOrd="1" destOrd="0" parTransId="{A5BA856F-CDD5-467F-AED9-A6F53B78CA73}" sibTransId="{3E3C9E13-D532-4240-861B-61465A101B7E}"/><dgm:cxn modelId="{B9EA87D1-4218-46BE-A635-A8D943634C3D}" srcId="{85EE8DA9-04DC-455E-BEBE-E95B1B8E8B02}" destId="{FAC1D642-4131-4165-956D-4755DF760E9B}" srcOrd="0" destOrd="0" parTransId="{3B866494-B66B-47F7-8E61-065A264561F8}" sibTransId="{1BF5E5EF-C969-48A4-98E6-E2BF08C5EE4D}"/><dgm:cxn modelId="{1021EFD2-4654-43CE-AE1A-05A6D92DA536}" type="presOf" srcId="{1BF5E5EF-C969-48A4-98E6-E2BF08C5EE4D}" destId="{5AEB064E-6249-4BCE-9AB5-DCDD47D35370}" srcOrd="1" destOrd="0" presId="urn:microsoft.com/office/officeart/2005/8/layout/process2"/><dgm:cxn modelId="{79DA54DF-AF8D-4777-AE1B-6BF13D0185ED}" type="presOf" srcId="{FAC1D642-4131-4165-956D-4755DF760E9B}" destId="{CF8D8D67-02F6-4BC6-AC36-E7F553406E0E}" srcOrd="0" destOrd="0" presId="urn:microsoft.com/office/officeart/2005/8/layout/process2"/><dgm:cxn modelId="{378C1FE8-07EF-4720-BD4F-550CF67AF24A}" type="presOf" srcId="{CE9C2ADF-3546-4D19-879D-AA1F0A6B6A00}" destId="{06FF23AE-5139-4417-AC57-FE8A80B517B9}" srcOrd="0" destOrd="0" presId="urn:microsoft.com/office/officeart/2005/8/layout/process2"/><dgm:cxn modelId="{AE8E1CEC-1625-4BF2-805C-06C338722376}" type="presOf" srcId="{1BF5E5EF-C969-48A4-98E6-E2BF08C5EE4D}" destId="{3BD5F3ED-C9DA-45B5-B47E-7C8B2178E406}" srcOrd="0" destOrd="0" presId="urn:microsoft.com/office/officeart/2005/8/layout/process2"/><dgm:cxn modelId="{6BDE2AED-AFA3-4FB2-A416-3B2150C32B92}" srcId="{85EE8DA9-04DC-455E-BEBE-E95B1B8E8B02}" destId="{028CE4FE-C1CA-4243-AC43-8A3B69987633}" srcOrd="3" destOrd="0" parTransId="{F361823E-B6D5-4600-B509-D28A919D22BA}" sibTransId="{7DE6B735-D8BA-4383-8518-E7F188E33349}"/><dgm:cxn modelId="{F1106F86-1307-4CFA-8B9E-A1716F3E96DD}" type="presParOf" srcId="{FBBDC216-FD4E-4F75-9122-C693ECF22FAA}" destId="{CF8D8D67-02F6-4BC6-AC36-E7F553406E0E}" srcOrd="0" destOrd="0" presId="urn:microsoft.com/office/officeart/2005/8/layout/process2"/><dgm:cxn modelId="{87889125-86C5-41DD-89C9-996DD390A9E2}" type="presParOf" srcId="{FBBDC216-FD4E-4F75-9122-C693ECF22FAA}" destId="{3BD5F3ED-C9DA-45B5-B47E-7C8B2178E406}" srcOrd="1" destOrd="0" presId="urn:microsoft.com/office/officeart/2005/8/layout/process2"/><dgm:cxn modelId="{0AF6645B-623E-4884-BDBD-975FC7F2CC88}" type="presParOf" srcId="{3BD5F3ED-C9DA-45B5-B47E-7C8B2178E406}" destId="{5AEB064E-6249-4BCE-9AB5-DCDD47D35370}" srcOrd="0" destOrd="0" presId="urn:microsoft.com/office/officeart/2005/8/layout/process2"/><dgm:cxn modelId="{5088056C-FA4B-4F45-B272-AEA7B8820275}" type="presParOf" srcId="{FBBDC216-FD4E-4F75-9122-C693ECF22FAA}" destId="{2CE34339-7BFE-4237-A512-63B0485362FF}" srcOrd="2" destOrd="0" presId="urn:microsoft.com/office/officeart/2005/8/layout/process2"/><dgm:cxn modelId="{B240C0FD-E0BC-40F2-9D07-9B81D85CDC13}" type="presParOf" srcId="{FBBDC216-FD4E-4F75-9122-C693ECF22FAA}" destId="{2E5D365C-8143-45DB-BC59-E2246545D519}" srcOrd="3" destOrd="0" presId="urn:microsoft.com/office/officeart/2005/8/layout/process2"/><dgm:cxn modelId="{8798B843-EE34-4E6C-8F15-F8578392CF14}" type="presParOf" srcId="{2E5D365C-8143-45DB-BC59-E2246545D519}" destId="{CE053936-2CDC-4F1A-AFC0-510D7BE55341}" srcOrd="0" destOrd="0" presId="urn:microsoft.com/office/officeart/2005/8/layout/process2"/><dgm:cxn modelId="{D5E4B86C-5D30-4016-8319-0A5A01D87E0F}" type="presParOf" srcId="{FBBDC216-FD4E-4F75-9122-C693ECF22FAA}" destId="{06FF23AE-5139-4417-AC57-FE8A80B517B9}" srcOrd="4" destOrd="0" presId="urn:microsoft.com/office/officeart/2005/8/layout/process2"/><dgm:cxn modelId="{B463E3F4-D16E-4E2D-AB92-36DE032BCA65}" type="presParOf" srcId="{FBBDC216-FD4E-4F75-9122-C693ECF22FAA}" destId="{F57D250A-67D8-41EF-AFCF-2442BA3F2D23}" srcOrd="5" destOrd="0" presId="urn:microsoft.com/office/officeart/2005/8/layout/process2"/><dgm:cxn modelId="{4E3AEED8-C13D-49EB-A62A-5ED6DA3B2310}" type="presParOf" srcId="{F57D250A-67D8-41EF-AFCF-2442BA3F2D23}" destId="{55BA79EA-8102-44BD-82F2-C7799D9B298B}" srcOrd="0" destOrd="0" presId="urn:microsoft.com/office/officeart/2005/8/layout/process2"/><dgm:cxn modelId="{3C7F24C8-6224-4FA7-BEBC-37CF0EA7FB0E}" type="presParOf" srcId="{FBBDC216-FD4E-4F75-9122-C693ECF22FAA}" destId="{0F81E002-8D1F-4D4C-BDDC-BFC08B7ECC2E}" srcOrd="6" destOrd="0" presId="urn:microsoft.com/office/officeart/2005/8/layout/process2"/><dgm:cxn modelId="{41F2E4CB-51E6-4541-824B-FDDB8418CE54}" type="presParOf" srcId="{FBBDC216-FD4E-4F75-9122-C693ECF22FAA}" destId="{85F6C259-8509-4F54-8CC0-BBC15F1C043B}" srcOrd="7" destOrd="0" presId="urn:microsoft.com/office/officeart/2005/8/layout/process2"/><dgm:cxn modelId="{9369FFE0-DF2E-4EA5-8826-52BD6B6AFBFB}" type="presParOf" srcId="{85F6C259-8509-4F54-8CC0-BBC15F1C043B}" destId="{3B8DD56D-B690-4851-91A9-E833B81AE722}" srcOrd="0" destOrd="0" presId="urn:microsoft.com/office/officeart/2005/8/layout/process2"/><dgm:cxn modelId="{95BC9408-AC6C-4EE5-8BF6-CCB471F46E48}" type="presParOf" srcId="{FBBDC216-FD4E-4F75-9122-C693ECF22FAA}" destId="{1CDBEB51-C06C-4495-9F1F-B3A13501E2CD}" srcOrd="8" destOrd="0" presId="urn:microsoft.com/office/officeart/2005/8/layout/process2"/></dgm:cxnLst><dgm:bg/><dgm:whole/><dgm:extLst><a:ext uri="http://schemas.microsoft.com/office/drawing/2008/diagram"><dsp:dataModelExt xmlns:dsp="http://schemas.microsoft.com/office/drawing/2008/diagram" relId="rId42" minVer="http://schemas.openxmlformats.org/drawingml/2006/diagram"/></a:ext></dgm:extLst></dgm:dataModel>